pva_resimagenet_app/__init__.py
pva_resimagenet_app/__main__.py
pva_resimagenet_app/app.py
pva_resimagenet_app/data/load_icon.gif
pva_resimagenet_app-0.0.5.dist-info/LICENSE
pva_resimagenet_app-0.0.5.dist-info/METADATA
pva_resimagenet_app-0.0.5.dist-info/WHEEL
pva_resimagenet_app-0.0.5.dist-info/top_level.txt
pva_resimagenet_app-0.0.5.dist-info/RECORD
