Metadata-Version: 2.1
Name: pva-resimagenet-app
Version: 0.0.5
Summary: An application that uses ResImageNet to restore old photos.
Home-page: https://github.com/Tailtoon/ResImageNet
Author: Vadim Pashkin
Author-email: vaplev@mail.ru
Project-URL: Bug Tracker, https://github.com/Tailtoon/ResImageNet/issues
Classifier: Development Status :: 3 - Alpha
Classifier: Programming Language :: Python :: 3
Classifier: License :: OSI Approved :: BSD License
Classifier: Operating System :: OS Independent
Requires-Python: ==3.8.10
License-File: LICENSE
Requires-Dist: scikit-image
Requires-Dist: numpy
Requires-Dist: pyside2
Requires-Dist: torch
Requires-Dist: torchvision
Requires-Dist: torchaudio
Requires-Dist: torchinfo
Requires-Dist: pva-resimagenet
